README.txt
setup.py
dist_plone/__init__.py
dist_plone/dist_plone.py
dist_plone/export.py
dist_plone/itarfile.py
dist_plone/tarfile.patch
dist_plone/platforms/__init__.py
dist_plone/platforms/independent.py
dist_plone/platforms/rpm.py
docs/HISTORY.txt
plone/__init__.py
plone.recipe.plone.egg-info/PKG-INFO
plone.recipe.plone.egg-info/SOURCES.txt
plone.recipe.plone.egg-info/dependency_links.txt
plone.recipe.plone.egg-info/entry_points.txt
plone.recipe.plone.egg-info/namespace_packages.txt
plone.recipe.plone.egg-info/requires.txt
plone.recipe.plone.egg-info/top_level.txt
plone.recipe.plone.egg-info/zip-safe
plone/recipe/__init__.py
plone/recipe/plone/__init__.py
plone/recipe/plone/recipe.py