Metadata-Version: 1.0
Name: plone.recipe.plone
Version: 3.1.6
Summary: Install Plone
Home-page: http://svn.plone.org/svn/plone/dist/plone.recipe.plone
Author: Martin Aspeli
Author-email: optilude@gmx.net
License: ZPL 2.1
Platform: UNKNOWN
Classifier: License :: OSI Approved :: Zope Public License
Classifier: Framework :: Plone
Classifier: Programming Language :: Python
